furiosa/server/__init__.py
furiosa/server/errors.py
furiosa/server/git_version.txt
furiosa/server/model.py
furiosa/server/py.typed
furiosa/server/registry.py
furiosa/server/repository.py
furiosa/server/server.py
furiosa/server/settings.py
furiosa/server/api/__init__.py
furiosa/server/api/cli/__init__.py
furiosa/server/api/cli/main.py
furiosa/server/api/grpc/__init__.py
furiosa/server/api/grpc/converters.py
furiosa/server/api/grpc/server.py
furiosa/server/api/grpc/servicers.py
furiosa/server/api/grpc/generated/__init__.py
furiosa/server/api/grpc/generated/model_repository_pb2.py
furiosa/server/api/grpc/generated/model_repository_pb2.pyi
furiosa/server/api/grpc/generated/model_repository_pb2_grpc.py
furiosa/server/api/grpc/generated/predict_pb2.py
furiosa/server/api/grpc/generated/predict_pb2.pyi
furiosa/server/api/grpc/generated/predict_pb2_grpc.py
furiosa/server/api/rest/__init__.py
furiosa/server/api/rest/app.py
furiosa/server/api/rest/endpoints.py
furiosa/server/api/rest/server.py
furiosa/server/handlers/__init__.py
furiosa/server/handlers/predict.py
furiosa/server/handlers/repository.py
furiosa/server/types/__init__.py
furiosa/server/types/model_repository.py
furiosa/server/types/predict.py
furiosa/server/utils/loader.py
furiosa_server-0.10.2.dist-info/entry_points.txt
furiosa_server-0.10.2.dist-info/WHEEL
furiosa_server-0.10.2.dist-info/METADATA
furiosa_server-0.10.2.dist-info/RECORD
