Metadata-Version: 2.1
Name: furiosa-server
Version: 0.10.2
Summary: FuriosaAI model server interacting Furiosa NPU.
Author-email: "FurioaAI, Inc." <pkg@furiosa.ai>
Requires-Python: ~=3.8
Classifier: Development Status :: 4 - Beta
Classifier: Environment :: Console
Classifier: Environment :: Web Environment
Classifier: Intended Audience :: Developers
Classifier: Intended Audience :: System Administrators
Classifier: License :: OSI Approved :: Apache Software License
Classifier: Programming Language :: Python :: 3
Classifier: Programming Language :: Python :: 3.8
Classifier: Programming Language :: Python :: 3.9
Classifier: Programming Language :: Python :: 3.10
Classifier: Topic :: Software Development :: Libraries :: Python Modules
Classifier: Topic :: Scientific/Engineering :: Artificial Intelligence
Requires-Dist: furiosa-runtime == 0.10.*
Requires-Dist: fastapi
Requires-Dist: httpx
Requires-Dist: pydantic-settings
Requires-Dist: grpcio-tools
Requires-Dist: protobuf
Requires-Dist: toml
Requires-Dist: typer
Requires-Dist: uvicorn
Requires-Dist: openvino ; extra == "openvino"
Requires-Dist: datamodel-code-generator ; extra == "test"
Requires-Dist: mypy ; extra == "test"
Requires-Dist: mypy-protobuf ; extra == "test"
Requires-Dist: mypy-extensions ; extra == "test"
Requires-Dist: pytest >=2.7.3 ; extra == "test"
Requires-Dist: pytest ; extra == "test"
Requires-Dist: pytest-asyncio ~= 0.17.2 ; extra == "test"
Requires-Dist: pytest-cov ; extra == "test"
Requires-Dist: requests ; extra == "test"
Requires-Dist: ruff ; extra == "test"
Requires-Dist: types-PyYAML ; extra == "test"
Requires-Dist: types-protobuf ; extra == "test"
Project-URL: Bug Tracker, https://github.com/furiosa-ai/furiosa-sdk/issues
Project-URL: Documentation, https://furiosa-ai.github.io/docs
Project-URL: Home, https://furiosa.ai
Project-URL: Source Code, https://github.com/furiosa-ai/furiosa-sdk
Provides-Extra: openvino
Provides-Extra: test
